README.md
setup.cfg
setup.py
dist_new/Binomialdistribution.py
dist_new/Gaussiandistribution.py
dist_new/Generaldistribution.py
dist_new/__init__.py
dist_new.egg-info/PKG-INFO
dist_new.egg-info/SOURCES.txt
dist_new.egg-info/dependency_links.txt
dist_new.egg-info/not-zip-safe
dist_new.egg-info/top_level.txt